singleton_admin/__init__.py
singleton_admin/admin.py
singleton_admin-1.0.0.dist-info/DESCRIPTION.rst
singleton_admin-1.0.0.dist-info/METADATA
singleton_admin-1.0.0.dist-info/RECORD
singleton_admin-1.0.0.dist-info/WHEEL
singleton_admin-1.0.0.dist-info/metadata.json
singleton_admin-1.0.0.dist-info/top_level.txt
