Metadata-Version: 1.1
Name: singleton-admin
Version: 1.0.0
Summary: A Django app that will only allow one instance of a model to be created via the admin site.
Home-page: https://github.com/tdsymonds/singleton_admin
Author: Tom Symonds
Author-email: tdsymonds@hotmail.com
License: MIT License
Keywords: admin singleton
Platform: UNKNOWN
Classifier: Environment :: Web Environment
Classifier: Framework :: Django
Classifier: Intended Audience :: Developers
Classifier: License :: OSI Approved :: MIT License
Classifier: Operating System :: OS Independent
Classifier: Programming Language :: Python
Classifier: Programming Language :: Python :: 2.7
Classifier: Topic :: Internet :: WWW/HTTP
Classifier: Topic :: Internet :: WWW/HTTP :: Dynamic Content
